{
  "type": "forge:conditional",
  "recipes": [
    {
      "conditions": [
        {
          "type": "forge:mod_loaded",
          "modid": "thermal_expansion"
        }
      ],
      "recipe": {
        "type": "useless_mod:advanced_alloy_furnace",
        "ingredients": [
          {
            "ingredient":
            {
              "item": "thermal:obsidian_glass"
            },
            "count": 64
          },
          {
            "ingredient": [
              {
                "tag": "forge:ingots/enderium"
              },
              {
                "tag": "forge:dusts/enderium"
              }
            ],
            "count": 32
          }
        ],
        "mold": {
          "item": "thermal:machine_smelter"
        },
        "catalyst": {
          "tag": "useless_mod:useless_ingots",
          "count": 1
        },
        "results": [
          {
            "item": "thermal:enderium_glass",
            "count": 64
          }
        ],
        "energy": 153600,
        "process_time": 40
      }
    }
  ]
}